required/__init__.py
required/decorator.py
required/dsl.py
required/exceptions.py
required/expressions.py
required/grammer.lark
required/requires.py
required-0.4.0.dist-info/LICENSE
required-0.4.0.dist-info/METADATA
required-0.4.0.dist-info/WHEEL
required-0.4.0.dist-info/top_level.txt
required-0.4.0.dist-info/RECORD
